{
"meta":{"test_sets":[],"test_metrics":[],"learn_metrics":[{"best_value":"Min","name":"Logloss"}],"launch_mode":"Train","parameters":"","iteration_count":10,"learn_sets":["learn"],"name":"experiment"},
"iterations":[
{"learn":[0.6009908971],"iteration":0,"passed_time":0.001060494737,"remaining_time":0.009544452637},
{"learn":[0.5504672942],"iteration":1,"passed_time":0.00196459737,"remaining_time":0.007858389479},
{"learn":[0.5057715721],"iteration":2,"passed_time":0.002853574755,"remaining_time":0.006658341094},
{"learn":[0.4767495064],"iteration":3,"passed_time":0.003737328677,"remaining_time":0.005605993015},
{"learn":[0.4539844942],"iteration":4,"passed_time":0.004677220206,"remaining_time":0.004677220206},
{"learn":[0.4380959844],"iteration":5,"passed_time":0.005683439784,"remaining_time":0.003788959856},
{"learn":[0.4188767004],"iteration":6,"passed_time":0.007126231973,"remaining_time":0.003054099417},
{"learn":[0.4051215702],"iteration":7,"passed_time":0.008694251769,"remaining_time":0.002173562942},
{"learn":[0.3908146029],"iteration":8,"passed_time":0.009696266566,"remaining_time":0.001077362952},
{"learn":[0.3811826478],"iteration":9,"passed_time":0.01066472378,"remaining_time":0}
]}